{"indicator":"15.5.1","layout":"indicator","permalink":"/15-5-1/","sdg_goal":"15","data_non_statistical":false,"goal_meta_link_text":"United Nations Sustainable Development Goals Metadata (PDF 440 KB)","graph_type":"line","indicator_name":"Red List Index","indicator_sort_order":"15-05-01","published":true,"reporting_status":"complete","target":"Take urgent and significant action to reduce the degradation of natural habitats, halt the loss of biodiversity and, by 2020, protect and prevent the extinction of threatened species","target_id":"15.5","graph_title":"Red List Index","un_custodian_agency":"International Union for Conservation of Nature (IUCN) BirdLife International (BLI)","un_designated_tier":"1","data_show_map":false,"source_active_1":true,"source_url_text_1":"Link to source","source_active_2":false,"source_url_text_2":"Link to Source","source_active_3":false,"source_url_3":"Link to source","source_active_4":false,"source_url_text_4":"Link to source","source_active_5":false,"source_url_text_5":"Link to source","source_active_6":false,"source_url_text_6":"Link to source","title":"Untitled","data_provider":"IUCN BLI","frequency":"Annual","data_source":"UN SDG Global Database","unit_of_measurement":"Score","local_indicator_definition":"Red List Index","global_indicator_definition":"Red List Index","national_data_update_url_text":"2019-06-19: see changes on GitHub","national_data_update_url":"https://github.com/sustainabledevelopment-Namibia/data/commit/4e76aedb2009e6b4bdc5691262fc210641220faf","national_metadata_update_url_text":"2019-06-25: see changes on GitHub","national_metadata_update_url":"https://github.com/sustainabledevelopment-Namibia/data/commit/608d4c18f4c210c817c1ffe015d305ffa3af8ad7","page_content":""}